{
    "slug": "txmn_gectile",
    "name_trans": "txmn_gectile_name",
    "description_trans": "txmn_gectile_descr",
    "category_trans": "txmn_gectile_category",
    "ai": "RandomAI",
    "moveset": [
        {
            "level_learned": 2,
            "technique": "technique_splinter"
        },
        {
            "level_learned": 2,
            "technique": "technique_peregrine"
        },
        {
            "level_learned": 2,
            "technique": "technique_whirlwind"
        }
    ],
    "shape": "Humanoid",
    "types": [
        "Wood"
    ],
    "weight": 25
}
