{
    "slug": "txmn_ruption",
    "name_trans": "txmn_ruption_name",
    "description_trans": "txmn_ruption_descr",
    "category_trans": "txmn_ruption_category",
    "ai": "RandomAI",
    "moveset": [
        {
            "level_learned": 2,
            "technique": "technique_berserk"
        },
        {
            "level_learned": 2,
            "technique": "technique_fume"
        },
        {
            "level_learned": 2,
            "technique": "technique_kindling_flame"
        }
    ],
    "shape": "Brute",
    "sprites": {
        "battle1": "gfx/sprites/battle/ruption-front.png",
        "battle2": "gfx/sprites/battle/ruption-back.png",
        "menu1": "gfx/sprites/battle/ruption-menu01.png",
        "menu2": "gfx/sprites/battle/ruption-menu02.png"
    },
    "types": [
        "Fire"
    ],
    "weight": 25
}
