{
    "slug": "agnidon",
    "category": "false_dragon",
    "moveset": [
        {
            "level_learned": 2,
            "technique": "fire_claw"
        },
        {
            "level_learned": 2,
            "technique": "fire_ball"
        },
        {
            "level_learned": 6,
            "technique": "one_two"
        },
        {
            "level_learned": 8,
            "technique": "saber"
        },
        {
            "level_learned": 12,
            "technique": "fume"
        },
        {
            "level_learned": 28,
            "technique": "kindling_flame"
        },
        {
            "level_learned": 32,
            "technique": "energy_claws"
        },
        {
            "level_learned": 34,
            "technique": "breathe_fire"
        },
        {
            "level_learned": 44,
            "technique": "take_cover"
        },
        {
            "level_learned": 48,
            "technique": "muddle"
        },
        {
            "level_learned": 52,
            "technique": "supernova"
        }
    ],
    "evolutions": [
        {
            "at_level": 36,
            "monster_slug": "agnigon"
        }
    ],
    "history": [
        {
            "mon_slug": "agnite",
            "evo_stage": "basic"
        },
        {
            "mon_slug": "agnigon",
            "evo_stage": "stage2"
        }
    ],
    "tags": ["dragon", "coastal", "desert", "mountains"],
    "shape": "dragon",
    "stage": "stage1",
    "types": [
        "fire"
    ],
    "possible_genders": ["male", "female"],
    "txmn_id": 14,
    "height": 320,
    "weight": 230,
    "catch_rate": 70.0,
    "lower_catch_resistance": 0.9,
    "upper_catch_resistance": 1.15
}
