{
    "slug": "arthrobolt",
    "category": "foreman",
    "ai": "RandomAI",
    "moveset": [
        {
            "level_learned": 2,
            "technique": "beam"
        },
        {
            "level_learned": 2,
            "technique": "surge"
        },
        {
            "level_learned": 2,
            "technique": "thunderclap"
        }
    ],
    "shape": "Humanoid",
    "types": [
        "Metal"
    ],
    "weight": 25,
    "catch_rate": 45.0,
    "lower_catch_resistance": 0.85,
    "upper_catch_resistance": 1.1
}