{
    "slug": "bamboon",
    "category": "prehensile",
    "ai": "RandomAI",
    "moveset": [
        {
            "level_learned": 2,
            "technique": "blade"
        },
        {
            "level_learned": 2,
            "technique": "clamp_on"
        },
        {
            "level_learned": 2,
            "technique": "ram"
        }
    ],
    "evolutions": [],
    "shape": "sprite",
    "types": [
        "wood"
    ],
    "possible_genders": ["male", "female"],
    "txmn_id": 27,
    "height": 120,
    "weight": 40,
    "catch_rate": 120.0,
    "lower_catch_resistance": 0.95,
    "upper_catch_resistance": 1.05
}
