{
    "slug": "miaownolith",
    "category": "desolate",
    "moveset": [
        {
            "level_learned": 2,
            "technique": "eyebite"
        },
        {
            "level_learned": 2,
            "technique": "feint"
        },
        {
            "level_learned": 6,
            "technique": "shuriken"
        },
        {
            "level_learned": 8,
            "technique": "slice"
        },
        {
            "level_learned": 12,
            "technique": "sand_spray"
        },
        {
            "level_learned": 20,
            "technique": "petrify"
        },
        {
            "level_learned": 24,
            "technique": "fluff_up"
        },
        {
            "level_learned": 28,
            "technique": "overgrowth"
        },
        {
            "level_learned": 36,
            "technique": "oedipus"
        }
    ],
    "evolutions": [],
    "history": [
        {
            "mon_slug": "memnomnom",
            "evo_stage": "basic"
        }
    ],
    "tags": ["hunter"],
    "shape": "hunter",
    "stage": "stage1",
    "types": [
        "metal",
        "earth"
    ],
    "possible_genders": ["male", "female"],
    "txmn_id": 20,
    "height": 210,
    "weight": 255,
    "catch_rate": 70.0,
    "lower_catch_resistance": 0.95,
    "upper_catch_resistance": 1.25
}
