{
    "slug": "qetzlrokilus",
    "category": "long_winged",
    "moveset": [
        {
            "level_learned": 1,
            "technique": "peck"
        },
        {
            "level_learned": 1,
            "technique": "kindling_flame"
        },
        {
            "level_learned": 4,
            "technique": "sand_spray"
        },
        {
            "level_learned": 7,
            "technique": "stampede"
        },
        {
            "level_learned": 13,
            "technique": "fire_shield"
        },
        {
            "level_learned": 16,
            "technique": "arcane_eye"
        },
        {
            "level_learned": 19,
            "technique": "breathe_fire"
        },
        {
            "level_learned": 43,
            "technique": "peregrine"
        },
        {
            "level_learned": 46,
            "technique": "all_in"
        },
        {
            "level_learned": 52,
            "technique": "flamethrower"
        }
    ],
    "evolutions": [],
    "history": [
        {
            "mon_slug": "metesaur",
            "evo_stage": "basic"
        }
    ],
    "tags": ["flier", "jungle", "mountains"],
    "shape": "flier",
    "stage": "stage1",
    "types": [
        "earth",
        "fire"
    ],
    "possible_genders": ["male", "female"],
    "txmn_id": 203,
    "height": 183,
    "weight": 41,
    "catch_rate": 70.0,
    "lower_catch_resistance": 0.9,
    "upper_catch_resistance": 1.15
}

