{
  "tech_id": 33,
  "accuracy": 0.8,
  "animation": "rockfall_193",
  "effects": [
    "give exhausted,target",
    "splash 2"
  ],
  "flip_axes": "",
  "is_fast": false,
  "potency": 0.8,
  "power": 2.25,
  "range": "ranged",
  "recharge": 3,
  "sfx": "sfx_crumble3",
  "slug": "avalanche",
  "sort": "damage",
  "target": {
    "enemy_monster": true,
    "enemy_team": false,
    "enemy_trainer": false,
    "own_monster": false,
    "own_team": false,
    "own_trainer": false
  },
  "category": "powerful",
  "tags": ["Calamity"],
  "types": [
    "earth"
  ],
  "use_failure": "combat_miss",
  "use_success": null,
  "use_tech": "combat_used_x"
}