{
  "tech_id": 90,
  "accuracy": 0.8,
  "animation": "spikes_rock",
  "effects": [
    "give stuck,target",
    "damage"
  ],
  "flip_axes": "",
  "is_fast": false,
  "potency": 1,
  "power": 2.25,
  "range": "touch",
  "recharge": 2,
  "sfx": "sfx_blaster",
  "slug": "quicksand",
  "sort": "damage",
  "target": {
    "enemy_monster": true,
    "enemy_team": false,
    "enemy_trainer": false,
    "own_monster": false,
    "own_team": false,
    "own_trainer": false
  },
  "category": "simple",
  "tags": ["Ground"],
  "types": [
    "earth"
  ],
  "use_failure": "combat_miss",
  "use_success": null,
  "use_tech": "combat_used_x"
}